setup.cfg
setup.py
gav4/__init__.py
gav4/gav4.py
gav4.egg-info/PKG-INFO
gav4.egg-info/SOURCES.txt
gav4.egg-info/dependency_links.txt
gav4.egg-info/not-zip-safe
gav4.egg-info/requires.txt
gav4.egg-info/top_level.txt
tests/__init__.py
tests/data.py
tests/test_gav4.py