Metadata-Version: 1.1
Name: gav4
Version: 0.1.2
Summary: Google Analytics V4 API Compatibility Library
Home-page: https://github.com/googleanalytics/gav4-python
Author: Google Analytics Platform
Author-email: mcohoon+gav4-python@google.com
License: Apache 2.0
Platform: Posix; MacOS X; Windows
Classifier: Development Status :: 1 - Planning
Classifier: Intended Audience :: Developers
Classifier: License :: OSI Approved :: Apache Software License
Classifier: Operating System :: OS Independent
Classifier: Programming Language :: Python :: 2
Classifier: Programming Language :: Python :: 2.6
Classifier: Programming Language :: Python :: 2.7
Classifier: Programming Language :: Python :: 3
Classifier: Programming Language :: Python :: 3.4
Classifier: Topic :: Internet
